nxpy/__init__.py
nxpy/device_proxy.py
juniper_nxpy-0.4.2.dist-info/LICENSE
juniper_nxpy-0.4.2.dist-info/METADATA
juniper_nxpy-0.4.2.dist-info/WHEEL
juniper_nxpy-0.4.2.dist-info/top_level.txt
juniper_nxpy-0.4.2.dist-info/RECORD
