Metadata-Version: 2.1
Name: juniper-nxpy
Version: 0.4.2
Summary: nxpy: Network XML Python Proxy
Home-page: https://github.com/grnet/juniper-nxpy
Author: Leonidas Poulopoulos
Author-email: dev@noc.grnet.gr
License: UNKNOWN
Platform: UNKNOWN
Classifier: Programming Language :: Python :: 2
Classifier: License :: OSI Approved :: GNU General Public License v3 (GPLv3)
Classifier: Operating System :: OS Independent
Requires-Dist: lxml (>=3.4.0)
